[
    {
        "id": 1,
        "name": "Cuisinart ICE-100",
        "image": "images/SalesItem1.jpg",
        "price": 100.00
    },
    {
        "id": 2,
        "name": "Breville Smart Scoop",
        "image": "images/SalesItem2.jpg",
        "price": 150.00
    },
    {
        "id": 3,
        "name": "Whynter ICM-201SB",
        "image": "images/SalesItem3.jpg",
        "price": 200.00
    },
    {
        "id": 4,
        "name": "Lello 4080 Musso Lussino",
        "image": "images/SalesItem4.jpg",
        "price": 125.00
    },
    {
        "id": 5,
        "name": "Nostalgia ICMP400WD",
        "image": "images/SalesItem5.jpg",
        "price": 320.00
    },
    {
        "id": 6,
        "name": "Hamilton Beach 68330N",
        "image": "images/SalesItem6.jpg",
        "price": 1735.00
    },
    {
        "id": 7,
        "name": "KitchenAid KICA0WH",
        "image": "images/SalesItem1.jpg",
        "price": 140.00
    },
    {
        "id": 8,
        "name": "Aicok Ice Cream Maker",
        "image": "images/SalesItem2.jpg",
        "price": 245.00
    },
    {
        "id": 9,
        "name": "Yonanas 902 Classic",
        "image": "images/SalesItem3.jpg",
        "price": 350.00
    },
    {
        "id": 10,
        "name": "Zoku Ice Cream Maker",
        "image": "images/SalesItem4.jpg",
        "price": 855.00
    },
    {
        "id": 11,
        "name": "DeLonghi GM6000",
        "image": "images/SalesItem5.jpg",
        "price": 600.00
    },
    {
        "id": 12,
        "name": "Maxi-Matic EIM-520",
        "image": "images/SalesItem6.jpg",
        "price": 1650.00
    },
    {
        "id": 13,
        "name": "VonShef Ice Cream Maker",
        "image": "images/SalesItem1.jpg",
        "price": 370.00
    },
    {
        "id": 14,
        "name": "Gourmia GSI170",
        "image": "images/SalesItem2.jpg",
        "price": 675.00
    },
    {
        "id": 15,
        "name": "Vevor Commercial Ice Cream Machine",
        "image": "images/SalesItem3.jpg",
        "price": 880.00
    },
    {
        "id": 16,
        "name": "Waring Pro IC70",
        "image": "images/SalesItem4.jpg",
        "price": 815.00
    },
    {
        "id": 17,
        "name": "Cuisinart ICE-21",
        "image": "images/SalesItem5.jpg",
        "price": 390.00
    },
    {
        "id": 18,
        "name": "Lello 5030 Pro",
        "image": "images/SalesItem6.jpg",
        "price": 1595.00
    },
    {
        "id": 19,
        "name": "Ariete Gran Gelato",
        "image": "images/SalesItem1.jpg",
        "price": 100.00
    },
    {
        "id": 20,
        "name": "Margaritaville Bahamas",
        "image": "images/SalesItem2.jpg",
        "price": 105.00
    }
]
